prusalinkapi/__init__.py
prusalinkapi/__main__.py
prusalinkapi-0.0.5.dist-info/LICENSE
prusalinkapi-0.0.5.dist-info/METADATA
prusalinkapi-0.0.5.dist-info/WHEEL
prusalinkapi-0.0.5.dist-info/top_level.txt
prusalinkapi-0.0.5.dist-info/RECORD
